FugroTools/Request.py
FugroTools/__init__.py
FugroTools-0.0.7.dist-info/LICENSE
FugroTools-0.0.7.dist-info/METADATA
FugroTools-0.0.7.dist-info/WHEEL
FugroTools-0.0.7.dist-info/top_level.txt
FugroTools-0.0.7.dist-info/RECORD
