Metadata-Version: 2.1
Name: FugroTools
Version: 0.0.7
Summary: A small example package
Home-page: https://github.com/pypa/sampleproject
